irace/__init__.py
irace/client_test.py
irace/stats/__init__.py
irace/stats/client.py
irace/stats/constants.py
irace/stats/drivers.py
irace/stats/search.py
irace/stats/utils.py
iRace-0.0.1.dist-info/LICENSE
iRace-0.0.1.dist-info/METADATA
iRace-0.0.1.dist-info/WHEEL
iRace-0.0.1.dist-info/entry_points.txt
iRace-0.0.1.dist-info/top_level.txt
iRace-0.0.1.dist-info/RECORD
